chalpak/__init__.py
chalpak/app.py
chalpak/exceptions.py
chalpak/response.py
chalpak/routes.py
chalpak/schema.py
chalpak-0.2.4.dist-info/METADATA
chalpak-0.2.4.dist-info/WHEEL
chalpak-0.2.4.dist-info/top_level.txt
chalpak-0.2.4.dist-info/RECORD
